Metadata-Version: 2.1
Name: ipyparams
Version: 0.2.0
Summary: Send parameters/arguments to notebooks via URL query string parameters.
Home-page: https://github.com/nbgallery/ipyparams
Author: Bill Allen
Author-email: photo.allen@gmail.com
License: MIT
Keywords: jupyter,notebook,parameters,arguments,url,query
Platform: UNKNOWN
Classifier: Development Status :: 4 - Beta
Classifier: Topic :: Utilities
Classifier: License :: OSI Approved :: MIT License
Requires-Python: >=3.4, <4
